unifyname/__init__.py
unifyname/utils.py
unifyname-0.1.0.dist-info/LICENSE
unifyname-0.1.0.dist-info/METADATA
unifyname-0.1.0.dist-info/WHEEL
unifyname-0.1.0.dist-info/top_level.txt
unifyname-0.1.0.dist-info/RECORD
