Metadata-Version: 2.1
Name: unifyname
Version: 0.1.0
Summary: unifyname package for Python-Guide.org
Home-page: https://github.com/vincent-belz/unifyname
Author: Vincent Belz
Author-email: vincent.belz@loft.com.br
License: Copyright (c) 2017, Kenneth Reitz        
Platform: UNKNOWN
License-File: LICENSE
Requires-Dist: fuzzywuzzy
Requires-Dist: python-Levenshtein
Requires-Dist: pytest
Requires-Dist: pandas
